fastapi_rc/__init__.py
fastapi_rc/client.py
fastapi_rc/dependencies.py
fastapi_rc/keys.py
fastapi_rc/service.py
fastapi_rc-0.1.0.dist-info/METADATA
fastapi_rc-0.1.0.dist-info/WHEEL
fastapi_rc-0.1.0.dist-info/licenses/LICENSE
fastapi_rc-0.1.0.dist-info/RECORD
