Metadata-Version: 2.4
Name: fastapi-rc
Version: 0.1.0
Summary: Enterprise-grade Redis caching for FastAPI with full control and clean DI patterns
Project-URL: Homepage, https://pypi.org/project/fastapi-rc/
Project-URL: Repository, https://github.com/CarterPerez-dev/fastapi-rc
Project-URL: Issues, https://github.com/CarterPerez-dev/fastapi-rc/issues
Project-URL: Changelog, https://github.com/CarterPerez-dev/fastapi-rc/blob/main/CHANGELOG.md
License-File: LICENSE
Requires-Python: >=3.12
Requires-Dist: fastapi>=0.124.4
Requires-Dist: pydantic>=2.12.5
Requires-Dist: redis[hiredis]<8.0.0,>=7.0.0
Provides-Extra: dev
Requires-Dist: httpx<0.29.0,>=0.28.1; extra == 'dev'
Requires-Dist: mypy<2.0.0,>=1.19.0; extra == 'dev'
Requires-Dist: pre-commit<5.0.0,>=4.5.0; extra == 'dev'
Requires-Dist: pylint<5.0.0,>=4.0.4; extra == 'dev'
Requires-Dist: pytest-cov<8.0.0,>=7.0.0; extra == 'dev'
Requires-Dist: pytest<10.0.0,>=9.0.2; extra == 'dev'
Requires-Dist: ruff<0.15.0,>=0.14.8; extra == 'dev'
Requires-Dist: ty<0.1.0,>=0.0.1a32; extra == 'dev'
